Metadata-Version: 1.0
Name: hit-the-road-jack
Version: 0.3
Summary: And don't you come back no more
Home-page: https://github.com/octopyth/hit_the_road_jack
Author: Sam Rock
Author-email: sam.rock@octopyth.com
License: GNU
Platform: UNKNOWN
